playsmart/__init__.py
playsmart/__main__.py
playsmart/_version.py
playsmart/constants.py
playsmart/core.py
playsmart/exceptions.py
playsmart/py.typed
playsmart/structures.py
playsmart/utils.py
playsmart-0.2.4.dist-info/METADATA
playsmart-0.2.4.dist-info/WHEEL
playsmart-0.2.4.dist-info/entry_points.txt
playsmart-0.2.4.dist-info/licenses/LICENSE
playsmart-0.2.4.dist-info/RECORD
