Metadata-Version: 2.4
Name: playsmart
Version: 0.2.4
Summary: Simple and efficient compagnion tool for Playwright. Write reusable and maintainable E2E tests like a human.
Author-email: Tracktor SAS <sre@tracktor.fr>
Maintainer-email: Tracktor SAS <sre@tracktor.fr>
License-Expression: Apache-2.0
License-File: LICENSE
Classifier: Development Status :: 4 - Beta
Classifier: Environment :: Web Environment
Classifier: Intended Audience :: Developers
Classifier: License :: OSI Approved :: Apache Software License
Classifier: Natural Language :: English
Classifier: Operating System :: OS Independent
Classifier: Programming Language :: Python
Classifier: Programming Language :: Python :: 3
Classifier: Programming Language :: Python :: 3 :: Only
Classifier: Programming Language :: Python :: 3.10
Classifier: Programming Language :: Python :: 3.11
Classifier: Programming Language :: Python :: 3.12
Classifier: Programming Language :: Python :: 3.13
Classifier: Programming Language :: Python :: Implementation :: CPython
Classifier: Topic :: Internet :: WWW/HTTP
Classifier: Topic :: Software Development :: Libraries
Requires-Python: >=3.10
Requires-Dist: beautifulsoup4<5,>=4.13
Requires-Dist: minify-html<1,>=0.15
Requires-Dist: openai<2,>=1
Requires-Dist: playwright<2,>=1
